<?xml version="1.0" encoding="UTF-8"?>
<persistence version="2.1"
	xmlns="http://xmlns.jcp.org/xml/ns/persistence" xmlns:xsi="http://www.w3.org/2001/XMLSchema-instance"
	xsi:schemaLocation="http://xmlns.jcp.org/xml/ns/persistence http://xmlns.jcp.org/xml/ns/persistence/persistence_2_1.xsd">
	<persistence-unit name="CRUD_JavaEE_PU" transaction-type="RESOURCE_LOCAL">
		<provider>org.eclipse.persistence.jpa.PersistenceProvider</provider>
		<class>com.fulvio.persistencia.entities.Ciudadano</class>
		<class>com.fulvio.persistencia.entities.Direccion</class>
		<class>com.fulvio.persistencia.entities.Telefono</class>
		<class>com.fulvio.persistencia.entities.Pais</class>
		<class>com.fulvio.persistencia.entities.Sector</class>
		<class>com.fulvio.persistencia.entities.Ciudad</class>
		<exclude-unlisted-classes>false</exclude-unlisted-classes>
		<properties>
			<property name="eclipselink.ddl-generation" value="create-tables" />
			<property name="javax.persistence.jdbc.driver" value="com.mysql.jdbc.Driver" />
			<property name="javax.persistence.jdbc.url" value="jdbc:mysql://MacBookPro-Izzy.lan:3306/CRUD_JEE" />
			<property name="javax.persistence.jdbc.user" value="root" />
			<property name="javax.persistence.jdbc.password" value="root1234" />
		</properties>
	</persistence-unit>
</persistence>
